[
  {
    "original": "左リヤフェンダー・アーチゴム取替加工・テールランプASSY・泥除けゴム脱着・テールランプブラケット曲がり直し・折損溶接",
    "price": 38000,
    "invoiceId": "24103100-1",
    "items": [
      {
        "target": "ブラケット",
        "action": "曲がり直し",
        "positions": [
          "左"
        ],
        "memo": "リヤフェンダー・アーチゴム・テールランプASSY・泥除けゴム・テールランプ・折損",
        "unitPrice": null
      },
      {
        "target": "ブラケット",
        "action": "取替",
        "positions": [
          "左"
        ],
        "memo": "リヤフェンダー・アーチゴム・テールランプASSY・泥除けゴム・テールランプ・折損",
        "unitPrice": null
      },
      {
        "target": "ブラケット",
        "action": "加工",
        "positions": [
          "左"
        ],
        "memo": "リヤフェンダー・アーチゴム・テールランプASSY・泥除けゴム・テールランプ・折損",
        "unitPrice": null
      },
      {
        "target": "ブラケット",
        "action": "脱着",
        "positions": [
          "左"
        ],
        "memo": "リヤフェンダー・アーチゴム・テールランプASSY・泥除けゴム・テールランプ・折損",
        "unitPrice": null
      },
      {
        "target": "ブラケット",
        "action": "溶接",
        "positions": [
          "左"
        ],
        "memo": "リヤフェンダー・アーチゴム・テールランプASSY・泥除けゴム・テールランプ・折損",
        "unitPrice": null
      }
    ],
    "isSet": true,
    "status": "success",
    "errors": [],
    "setName": "左リヤフェンダー・アーチゴム取替加工・テールランプASSY・泥除けゴム脱着・テールランプブラケット曲がり直し・折損溶接",
    "setPrice": 38000
  },
  {
    "original": "リヤカーテンレール脱着・パイプ切断脱着溶接・リング10個交換（部品代金込み）",
    "price": 35000,
    "invoiceId": "24113102-1",
    "items": [
      {
        "target": "パイプ",
        "action": "交換",
        "positions": [],
        "memo": "リヤカーテンレール・脱着・リング10個（部品代金込み）",
        "unitPrice": null
      },
      {
        "target": "パイプ",
        "action": "脱着",
        "positions": [],
        "memo": "リヤカーテンレール・脱着・リング10個（部品代金込み）",
        "unitPrice": null
      },
      {
        "target": "パイプ",
        "action": "溶接",
        "positions": [],
        "memo": "リヤカーテンレール・脱着・リング10個（部品代金込み）",
        "unitPrice": null
      },
      {
        "target": "パイプ",
        "action": "切断",
        "positions": [],
        "memo": "リヤカーテンレール・脱着・リング10個（部品代金込み）",
        "unitPrice": null
      }
    ],
    "isSet": true,
    "status": "success",
    "errors": [],
    "setName": "リヤカーテンレール脱着・パイプ切断脱着溶接・リング10個交換（部品代金込み）",
    "setPrice": 35000
  },
  {
    "original": "燃料タンク点検",
    "price": 5000,
    "invoiceId": "24113103-1",
    "items": [
      {
        "target": "燃料タンク",
        "action": "点検",
        "positions": [],
        "memo": "",
        "unitPrice": 5000
      }
    ],
    "isSet": false,
    "status": "success",
    "errors": []
  },
  {
    "original": "バンパー・右フィニッシャー・グリル・インナーバンパー取替・左フィニッシャー曲がり直し・左右ヘッドライト・フォグランプ付替え",
    "price": 28000,
    "invoiceId": "24113104-1",
    "items": [
      {
        "target": "インナーバンパー",
        "action": "曲がり直し",
        "positions": [],
        "memo": "バンパー・右フィニッシャー・グリル・・左フィニッシャー・左右ヘッドライト・フォグランプえ",
        "unitPrice": null
      },
      {
        "target": "インナーバンパー",
        "action": "取替",
        "positions": [],
        "memo": "バンパー・右フィニッシャー・グリル・・左フィニッシャー・左右ヘッドライト・フォグランプえ",
        "unitPrice": null
      },
      {
        "target": "インナーバンパー",
        "action": "付替",
        "positions": [],
        "memo": "バンパー・右フィニッシャー・グリル・・左フィニッシャー・左右ヘッドライト・フォグランプえ",
        "unitPrice": null
      }
    ],
    "isSet": true,
    "status": "success",
    "errors": [],
    "setName": "バンパー・右フィニッシャー・グリル・インナーバンパー取替・左フィニッシャー曲がり直し・左右ヘッドライト・フォグランプ付替え",
    "setPrice": 28000
  },
  {
    "original": "右コーナーパネル脱着",
    "price": 3500,
    "invoiceId": "24113108-1",
    "items": [
      {
        "target": "コーナーパネル",
        "action": "脱着",
        "positions": [
          "右"
        ],
        "memo": "",
        "unitPrice": 3500
      }
    ],
    "isSet": false,
    "status": "success",
    "errors": []
  },
  {
    "original": "右ドアパネルASSY交換・バイザー張替・部品組み換え・フラッシャー交換・ミラー付替え",
    "price": 38000,
    "invoiceId": "24113108-1",
    "items": [
      {
        "target": "ドアパネル",
        "action": "交換",
        "positions": [
          "右"
        ],
        "memo": "ASSY・バイザー・部品組み換え・フラッシャー交換・ミラーえ",
        "unitPrice": null
      },
      {
        "target": "ドアパネル",
        "action": "張替",
        "positions": [
          "右"
        ],
        "memo": "ASSY・バイザー・部品組み換え・フラッシャー交換・ミラーえ",
        "unitPrice": null
      },
      {
        "target": "ドアパネル",
        "action": "付替",
        "positions": [
          "右"
        ],
        "memo": "ASSY・バイザー・部品組み換え・フラッシャー交換・ミラーえ",
        "unitPrice": null
      }
    ],
    "isSet": true,
    "status": "success",
    "errors": [],
    "setName": "右ドアパネルASSY交換・バイザー張替・部品組み換え・フラッシャー交換・ミラー付替え",
    "setPrice": 38000
  },
  {
    "original": "ドアメッキカバー脱着付替え加工",
    "price": 13000,
    "invoiceId": "24113108-1",
    "items": [
      {
        "target": "ドア",
        "action": "カバー",
        "positions": [],
        "memo": "メッキえ",
        "unitPrice": null
      },
      {
        "target": "ドア",
        "action": "加工",
        "positions": [],
        "memo": "メッキえ",
        "unitPrice": null
      },
      {
        "target": "ドア",
        "action": "脱着",
        "positions": [],
        "memo": "メッキえ",
        "unitPrice": null
      },
      {
        "target": "ドア",
        "action": "付替",
        "positions": [],
        "memo": "メッキえ",
        "unitPrice": null
      }
    ],
    "isSet": true,
    "status": "success",
    "errors": [],
    "setName": "ドアメッキカバー脱着付替え加工",
    "setPrice": 13000
  },
  {
    "original": "右フィニッシャー・エンドカバーインナーバンパーステイ取替修正・フォグカバー付替え",
    "price": 15000,
    "invoiceId": "24113108-1",
    "items": [
      {
        "target": "インナーバンパー",
        "action": "カバー",
        "positions": [
          "右"
        ],
        "memo": "フィニッシャー・エンドステイ・フォグカバーえ",
        "unitPrice": null
      },
      {
        "target": "インナーバンパー",
        "action": "取替",
        "positions": [
          "右"
        ],
        "memo": "フィニッシャー・エンドステイ・フォグカバーえ",
        "unitPrice": null
      },
      {
        "target": "インナーバンパー",
        "action": "修正",
        "positions": [
          "右"
        ],
        "memo": "フィニッシャー・エンドステイ・フォグカバーえ",
        "unitPrice": null
      },
      {
        "target": "インナーバンパー",
        "action": "付替",
        "positions": [
          "右"
        ],
        "memo": "フィニッシャー・エンドステイ・フォグカバーえ",
        "unitPrice": null
      }
    ],
    "isSet": true,
    "status": "success",
    "errors": [],
    "setName": "右フィニッシャー・エンドカバーインナーバンパーステイ取替修正・フォグカバー付替え",
    "setPrice": 15000
  },
  {
    "original": "プラットホーム左踊場脱着・ブラケットボルト2本取付・ねじ山修正",
    "price": 10000,
    "invoiceId": "24113111-1",
    "items": [
      {
        "target": "ブラケット",
        "action": "脱着",
        "positions": [],
        "memo": "プラットホーム左踊場・ボルト2本・ねじ山",
        "unitPrice": null
      },
      {
        "target": "ブラケット",
        "action": "取付",
        "positions": [],
        "memo": "プラットホーム左踊場・ボルト2本・ねじ山",
        "unitPrice": null
      },
      {
        "target": "ブラケット",
        "action": "修正",
        "positions": [],
        "memo": "プラットホーム左踊場・ボルト2本・ねじ山",
        "unitPrice": null
      }
    ],
    "isSet": true,
    "status": "success",
    "errors": [],
    "setName": "プラットホーム左踊場脱着・ブラケットボルト2本取付・ねじ山修正",
    "setPrice": 10000
  },
  {
    "original": "UDPC取付ボルト折れ込み修理・エンジンカバー・テールパイプ・ジャバラパイプ脱着・ねじ山修正",
    "price": 24000,
    "invoiceId": "24113113-1",
    "items": [
      {
        "target": "エンジンカバー",
        "action": "修理",
        "positions": [],
        "memo": "UDPCボルト折れ込み・・テールパイプ・ジャバラパイプ・ねじ山",
        "unitPrice": null
      },
      {
        "target": "エンジンカバー",
        "action": "脱着",
        "positions": [],
        "memo": "UDPCボルト折れ込み・・テールパイプ・ジャバラパイプ・ねじ山",
        "unitPrice": null
      },
      {
        "target": "エンジンカバー",
        "action": "取付",
        "positions": [],
        "memo": "UDPCボルト折れ込み・・テールパイプ・ジャバラパイプ・ねじ山",
        "unitPrice": null
      },
      {
        "target": "エンジンカバー",
        "action": "修正",
        "positions": [],
        "memo": "UDPCボルト折れ込み・・テールパイプ・ジャバラパイプ・ねじ山",
        "unitPrice": null
      }
    ],
    "isSet": true,
    "status": "success",
    "errors": [],
    "setName": "UDPC取付ボルト折れ込み修理・エンジンカバー・テールパイプ・ジャバラパイプ脱着・ねじ山修正",
    "setPrice": 24000
  },
  {
    "original": "右ドア建付け調整",
    "price": 8500,
    "invoiceId": "24113114-1",
    "items": [
      {
        "target": "ドア",
        "action": "調整",
        "positions": [
          "右"
        ],
        "memo": "建付け",
        "unitPrice": 8500
      }
    ],
    "isSet": false,
    "status": "success",
    "errors": []
  },
  {
    "original": "左サイドガード折損2カ所修正溶接・歯止め入れ折損修正溶接",
    "price": 18000,
    "invoiceId": "24113117-1",
    "items": [
      {
        "target": "サイドガード",
        "action": "溶接",
        "positions": [
          "左"
        ],
        "memo": "折損2カ所・歯止め入れ折損修正溶接",
        "unitPrice": null
      },
      {
        "target": "サイドガード",
        "action": "修正",
        "positions": [
          "左"
        ],
        "memo": "折損2カ所・歯止め入れ折損修正溶接",
        "unitPrice": null
      }
    ],
    "isSet": true,
    "status": "success",
    "errors": [],
    "setName": "左サイドガード折損2カ所修正溶接・歯止め入れ折損修正溶接",
    "setPrice": 18000
  },
  {
    "original": "右三角リフレクターブラケット製作取付加工・左右三角リフレクター取替",
    "price": 28000,
    "invoiceId": "24113117-1",
    "items": [
      {
        "target": "ブラケット",
        "action": "取替",
        "positions": [
          "右"
        ],
        "memo": "三角リフレクター・左右三角リフレクター",
        "unitPrice": null
      },
      {
        "target": "ブラケット",
        "action": "加工",
        "positions": [
          "右"
        ],
        "memo": "三角リフレクター・左右三角リフレクター",
        "unitPrice": null
      },
      {
        "target": "ブラケット",
        "action": "取付",
        "positions": [
          "右"
        ],
        "memo": "三角リフレクター・左右三角リフレクター",
        "unitPrice": null
      },
      {
        "target": "ブラケット",
        "action": "製作",
        "positions": [
          "右"
        ],
        "memo": "三角リフレクター・左右三角リフレクター",
        "unitPrice": null
      }
    ],
    "isSet": true,
    "status": "success",
    "errors": [],
    "setName": "右三角リフレクターブラケット製作取付加工・左右三角リフレクター取替",
    "setPrice": 28000
  },
  {
    "original": "左右コネクターホース脱着ステイ2本折損溶接",
    "price": 12000,
    "invoiceId": "24113117-1",
    "items": [
      {
        "target": "ホース",
        "action": "脱着",
        "positions": [
          "左"
        ],
        "memo": "右コネクターステイ2本折損",
        "unitPrice": null
      },
      {
        "target": "ホース",
        "action": "溶接",
        "positions": [
          "左"
        ],
        "memo": "右コネクターステイ2本折損",
        "unitPrice": null
      }
    ],
    "isSet": true,
    "status": "success",
    "errors": [],
    "setName": "左右コネクターホース脱着ステイ2本折損溶接",
    "setPrice": 12000
  },
  {
    "original": "右タイヤ灯脱着折損修正補強取り付け溶接",
    "price": 12000,
    "invoiceId": "24113121-1",
    "items": [
      {
        "target": "タイヤ灯",
        "action": "脱着",
        "positions": [
          "右"
        ],
        "memo": "折損補強取り付け",
        "unitPrice": null
      },
      {
        "target": "タイヤ灯",
        "action": "溶接",
        "positions": [
          "右"
        ],
        "memo": "折損補強取り付け",
        "unitPrice": null
      },
      {
        "target": "タイヤ灯",
        "action": "修正",
        "positions": [
          "右"
        ],
        "memo": "折損補強取り付け",
        "unitPrice": null
      }
    ],
    "isSet": true,
    "status": "success",
    "errors": [],
    "setName": "右タイヤ灯脱着折損修正補強取り付け溶接",
    "setPrice": 12000
  },
  {
    "original": "左サイドバンパーコーナーパイプ製作切替加工",
    "price": 15000,
    "invoiceId": "24113123-1",
    "items": [
      {
        "target": "パイプ",
        "action": "加工",
        "positions": [
          "左"
        ],
        "memo": "サイドバンパーコーナー",
        "unitPrice": null
      },
      {
        "target": "パイプ",
        "action": "製作",
        "positions": [
          "左"
        ],
        "memo": "サイドバンパーコーナー",
        "unitPrice": null
      },
      {
        "target": "パイプ",
        "action": "切替",
        "positions": [
          "左"
        ],
        "memo": "サイドバンパーコーナー",
        "unitPrice": null
      }
    ],
    "isSet": true,
    "status": "success",
    "errors": [],
    "setName": "左サイドバンパーコーナーパイプ製作切替加工",
    "setPrice": 15000
  },
  {
    "original": "リヤ右前側シャックル・ブラケット亀裂カット溶接",
    "price": 5000,
    "invoiceId": "24113124-1",
    "items": [
      {
        "target": "ブラケット",
        "action": "溶接",
        "positions": [],
        "memo": "リヤ右前側シャックル・亀裂カット",
        "unitPrice": 5000
      }
    ],
    "isSet": false,
    "status": "success",
    "errors": []
  },
  {
    "original": "左サイドバンパー前側コーナーパイプ製作切替加工",
    "price": 15000,
    "invoiceId": "24113126-1",
    "items": [
      {
        "target": "パイプ",
        "action": "加工",
        "positions": [
          "左"
        ],
        "memo": "サイドバンパー前側コーナー",
        "unitPrice": null
      },
      {
        "target": "パイプ",
        "action": "製作",
        "positions": [
          "左"
        ],
        "memo": "サイドバンパー前側コーナー",
        "unitPrice": null
      },
      {
        "target": "パイプ",
        "action": "切替",
        "positions": [
          "左"
        ],
        "memo": "サイドバンパー前側コーナー",
        "unitPrice": null
      }
    ],
    "isSet": true,
    "status": "success",
    "errors": [],
    "setName": "左サイドバンパー前側コーナーパイプ製作切替加工",
    "setPrice": 15000
  },
  {
    "original": "煽りドア補助装置4ヶ所切断取り換え加工",
    "price": 32000,
    "invoiceId": "24113127-1",
    "items": [
      {
        "target": "ドア",
        "action": "加工",
        "positions": [],
        "memo": "煽り補助装置4ヶ所取り換え",
        "unitPrice": null
      },
      {
        "target": "ドア",
        "action": "切断",
        "positions": [],
        "memo": "煽り補助装置4ヶ所取り換え",
        "unitPrice": null
      }
    ],
    "isSet": true,
    "status": "success",
    "errors": [],
    "setName": "煽りドア補助装置4ヶ所切断取り換え加工",
    "setPrice": 32000
  },
  {
    "original": "右前・左後ろ煽りドア補助装置２個取替",
    "price": 16000,
    "invoiceId": "24113128-1",
    "items": [
      {
        "target": "ドア",
        "action": "取替",
        "positions": [
          "右"
        ],
        "memo": "前・左後ろ煽り補助装置２個",
        "unitPrice": 16000
      }
    ],
    "isSet": false,
    "status": "success",
    "errors": []
  },
  {
    "original": "左サイドミラー脱着・サイドアーム修正",
    "price": 6500,
    "invoiceId": "24113129-1",
    "items": [
      {
        "target": "サイドミラー",
        "action": "脱着",
        "positions": [
          "左"
        ],
        "memo": "・サイドアーム",
        "unitPrice": null
      },
      {
        "target": "サイドミラー",
        "action": "修正",
        "positions": [
          "左"
        ],
        "memo": "・サイドアーム",
        "unitPrice": null
      }
    ],
    "isSet": true,
    "status": "success",
    "errors": [],
    "setName": "左サイドミラー脱着・サイドアーム修正",
    "setPrice": 6500
  },
  {
    "original": "エアタンク交換",
    "price": 8000,
    "invoiceId": "24113131-1",
    "items": [
      {
        "target": "エアタンク",
        "action": "交換",
        "positions": [],
        "memo": "",
        "unitPrice": 8000
      }
    ],
    "isSet": false,
    "status": "success",
    "errors": []
  },
  {
    "original": "エアタンク交換",
    "price": 8000,
    "invoiceId": "24113131-2",
    "items": [
      {
        "target": "エアタンク",
        "action": "交換",
        "positions": [],
        "memo": "",
        "unitPrice": 8000
      }
    ],
    "isSet": false,
    "status": "success",
    "errors": []
  },
  {
    "original": "リーフスプリングハンガーブラケット前側左右亀裂カット溶接",
    "price": 12000,
    "invoiceId": "24113136-1",
    "items": [
      {
        "target": "ブラケット",
        "action": "溶接",
        "positions": [],
        "memo": "リーフスプリングハンガー前側左右亀裂カット",
        "unitPrice": 12000
      }
    ],
    "isSet": false,
    "status": "success",
    "errors": []
  },
  {
    "original": "左右煽りドア補助装置点検・調整",
    "price": 8000,
    "invoiceId": "24113138-1",
    "items": [
      {
        "target": "ドア",
        "action": "点検",
        "positions": [
          "左"
        ],
        "memo": "右煽り補助装置・",
        "unitPrice": null
      },
      {
        "target": "ドア",
        "action": "調整",
        "positions": [
          "左"
        ],
        "memo": "右煽り補助装置・",
        "unitPrice": null
      }
    ],
    "isSet": true,
    "status": "success",
    "errors": [],
    "setName": "左右煽りドア補助装置点検・調整",
    "setPrice": 8000
  },
  {
    "original": "左右サイドガード亀裂溶接３ヶ所・巻き込み防止パイプ1本切替・３ヶ所折損溶接",
    "price": 33000,
    "invoiceId": "24113141-1",
    "items": [
      {
        "target": "サイドガード",
        "action": "溶接",
        "positions": [
          "左"
        ],
        "memo": "右亀裂３ヶ所・巻き込み防止パイプ1本・３ヶ所折損溶接",
        "unitPrice": null
      },
      {
        "target": "サイドガード",
        "action": "切替",
        "positions": [
          "左"
        ],
        "memo": "右亀裂３ヶ所・巻き込み防止パイプ1本・３ヶ所折損溶接",
        "unitPrice": null
      }
    ],
    "isSet": true,
    "status": "success",
    "errors": [],
    "setName": "左右サイドガード亀裂溶接３ヶ所・巻き込み防止パイプ1本切替・３ヶ所折損溶接",
    "setPrice": 33000
  },
  {
    "original": "左サイドガードステイ曲がり修正",
    "price": 12000,
    "invoiceId": "24113141-1",
    "items": [
      {
        "target": "サイドガード",
        "action": "修正",
        "positions": [
          "左"
        ],
        "memo": "ステイ曲がり",
        "unitPrice": 12000
      }
    ],
    "isSet": false,
    "status": "success",
    "errors": []
  },
  {
    "original": "バッテリースイッチ取り付けステイ製作取り付け加工",
    "price": 20000,
    "invoiceId": "24113142-1",
    "items": [
      {
        "target": "バッテリー",
        "action": "加工",
        "positions": [],
        "memo": "スイッチ取り付けステイ取り付け",
        "unitPrice": null
      },
      {
        "target": "バッテリー",
        "action": "製作",
        "positions": [],
        "memo": "スイッチ取り付けステイ取り付け",
        "unitPrice": null
      }
    ],
    "isSet": true,
    "status": "success",
    "errors": [],
    "setName": "バッテリースイッチ取り付けステイ製作取り付け加工",
    "setPrice": 20000
  },
  {
    "original": "左サイドガード2本曲がり修正及び亀裂溶接",
    "price": 28000,
    "invoiceId": "24113146-1",
    "items": [
      {
        "target": "サイドガード",
        "action": "溶接",
        "positions": [
          "左"
        ],
        "memo": "2本曲がり及び亀裂",
        "unitPrice": null
      },
      {
        "target": "サイドガード",
        "action": "修正",
        "positions": [
          "左"
        ],
        "memo": "2本曲がり及び亀裂",
        "unitPrice": null
      }
    ],
    "isSet": true,
    "status": "success",
    "errors": [],
    "setName": "左サイドガード2本曲がり修正及び亀裂溶接",
    "setPrice": 28000
  },
  {
    "original": "リヤゲート左締めフック分解清掃・グリスホース取替",
    "price": 32000,
    "invoiceId": "24113146-1",
    "items": [
      {
        "target": "ホース",
        "action": "分解",
        "positions": [],
        "memo": "リヤゲート左締めフック・グリス取替",
        "unitPrice": null
      },
      {
        "target": "ホース",
        "action": "清掃",
        "positions": [],
        "memo": "リヤゲート左締めフック・グリス取替",
        "unitPrice": null
      }
    ],
    "isSet": true,
    "status": "success",
    "errors": [],
    "setName": "リヤゲート左締めフック分解清掃・グリスホース取替",
    "setPrice": 32000
  },
  {
    "original": "左サイドガード1番ステイ製作取替加工",
    "price": 18000,
    "invoiceId": "24113151-1",
    "items": [
      {
        "target": "サイドガード",
        "action": "取替",
        "positions": [
          "左"
        ],
        "memo": "1番ステイ",
        "unitPrice": null
      },
      {
        "target": "サイドガード",
        "action": "加工",
        "positions": [
          "左"
        ],
        "memo": "1番ステイ",
        "unitPrice": null
      },
      {
        "target": "サイドガード",
        "action": "製作",
        "positions": [
          "左"
        ],
        "memo": "1番ステイ",
        "unitPrice": null
      }
    ],
    "isSet": true,
    "status": "success",
    "errors": [],
    "setName": "左サイドガード1番ステイ製作取替加工",
    "setPrice": 18000
  },
  {
    "original": "左右サイドガード腐食部12カ所切替加工",
    "price": 72000,
    "invoiceId": "24113151-1",
    "items": [
      {
        "target": "サイドガード",
        "action": "加工",
        "positions": [
          "左"
        ],
        "memo": "右腐食部12カ所",
        "unitPrice": null
      },
      {
        "target": "サイドガード",
        "action": "切替",
        "positions": [
          "左"
        ],
        "memo": "右腐食部12カ所",
        "unitPrice": null
      }
    ],
    "isSet": true,
    "status": "success",
    "errors": [],
    "setName": "左右サイドガード腐食部12カ所切替加工",
    "setPrice": 72000
  },
  {
    "original": "左サイドガード曲がり修正",
    "price": 8000,
    "invoiceId": "24113151-1",
    "items": [
      {
        "target": "サイドガード",
        "action": "修正",
        "positions": [
          "左"
        ],
        "memo": "曲がり",
        "unitPrice": 8000
      }
    ],
    "isSet": false,
    "status": "success",
    "errors": []
  },
  {
    "original": "左煽りドア補助装置交換",
    "price": 8000,
    "invoiceId": "24113154-1",
    "items": [
      {
        "target": "ドア",
        "action": "交換",
        "positions": [
          "左"
        ],
        "memo": "煽り補助装置",
        "unitPrice": 8000
      }
    ],
    "isSet": false,
    "status": "success",
    "errors": []
  },
  {
    "original": "運転席側ドアー捻じれ修理",
    "price": 8500,
    "invoiceId": "24113156-1",
    "items": [
      {
        "target": "ドア",
        "action": "修理",
        "positions": [
          "運転席"
        ],
        "memo": "側ー捻じれ",
        "unitPrice": 8500
      }
    ],
    "isSet": false,
    "status": "success",
    "errors": []
  },
  {
    "original": "DPFマフラーカバー取り付け溶接ナット切断取替加工4個",
    "price": 24000,
    "invoiceId": "24113157-1",
    "items": [
      {
        "target": "マフラーカバー",
        "action": "取替",
        "positions": [],
        "memo": "DPF取り付けナット4個",
        "unitPrice": null
      },
      {
        "target": "マフラーカバー",
        "action": "加工",
        "positions": [],
        "memo": "DPF取り付けナット4個",
        "unitPrice": null
      },
      {
        "target": "マフラーカバー",
        "action": "溶接",
        "positions": [],
        "memo": "DPF取り付けナット4個",
        "unitPrice": null
      },
      {
        "target": "マフラーカバー",
        "action": "切断",
        "positions": [],
        "memo": "DPF取り付けナット4個",
        "unitPrice": null
      }
    ],
    "isSet": true,
    "status": "success",
    "errors": [],
    "setName": "DPFマフラーカバー取り付け溶接ナット切断取替加工4個",
    "setPrice": 24000
  },
  {
    "original": "DPFマフラーカバーブラケット腐食部分補強取付溶接・カバー取り付け",
    "price": 8000,
    "invoiceId": "24113157-1",
    "items": [
      {
        "target": "マフラーカバー",
        "action": "カバー",
        "positions": [],
        "memo": "DPFブラケット腐食部分補強・取り付け",
        "unitPrice": null
      },
      {
        "target": "マフラーカバー",
        "action": "溶接",
        "positions": [],
        "memo": "DPFブラケット腐食部分補強・取り付け",
        "unitPrice": null
      },
      {
        "target": "マフラーカバー",
        "action": "取付",
        "positions": [],
        "memo": "DPFブラケット腐食部分補強・取り付け",
        "unitPrice": null
      }
    ],
    "isSet": true,
    "status": "success",
    "errors": [],
    "setName": "DPFマフラーカバーブラケット腐食部分補強取付溶接・カバー取り付け",
    "setPrice": 8000
  },
  {
    "original": "左右テールランプ交換・テールランプブラケット製作取付加工",
    "price": 44000,
    "invoiceId": "24123158-1",
    "items": [
      {
        "target": "ブラケット",
        "action": "加工",
        "positions": [
          "左"
        ],
        "memo": "右テールランプ・テールランプ",
        "unitPrice": null
      },
      {
        "target": "ブラケット",
        "action": "交換",
        "positions": [
          "左"
        ],
        "memo": "右テールランプ・テールランプ",
        "unitPrice": null
      },
      {
        "target": "ブラケット",
        "action": "取付",
        "positions": [
          "左"
        ],
        "memo": "右テールランプ・テールランプ",
        "unitPrice": null
      },
      {
        "target": "ブラケット",
        "action": "製作",
        "positions": [
          "左"
        ],
        "memo": "右テールランプ・テールランプ",
        "unitPrice": null
      }
    ],
    "isSet": true,
    "status": "success",
    "errors": [],
    "setName": "左右テールランプ交換・テールランプブラケット製作取付加工",
    "setPrice": 44000
  },
  {
    "original": "右ドア後ろメッキカバー取替",
    "price": 5000,
    "invoiceId": "24123160-1",
    "items": [
      {
        "target": "ドア",
        "action": "カバー",
        "positions": [
          "右"
        ],
        "memo": "後ろメッキ",
        "unitPrice": null
      },
      {
        "target": "ドア",
        "action": "取替",
        "positions": [
          "右"
        ],
        "memo": "後ろメッキ",
        "unitPrice": null
      }
    ],
    "isSet": true,
    "status": "success",
    "errors": [],
    "setName": "右ドア後ろメッキカバー取替",
    "setPrice": 5000
  },
  {
    "original": "カプラースイッチブラケット取付加工",
    "price": 12000,
    "invoiceId": "24123162-1",
    "items": [
      {
        "target": "ブラケット",
        "action": "加工",
        "positions": [],
        "memo": "カプラースイッチ",
        "unitPrice": null
      },
      {
        "target": "ブラケット",
        "action": "取付",
        "positions": [],
        "memo": "カプラースイッチ",
        "unitPrice": null
      }
    ],
    "isSet": true,
    "status": "success",
    "errors": [],
    "setName": "カプラースイッチブラケット取付加工",
    "setPrice": 12000
  },
  {
    "original": "燃料タンク点検・バンド２本取替",
    "price": 5000,
    "invoiceId": "24123163-1",
    "items": [
      {
        "target": "燃料タンク",
        "action": "取替",
        "positions": [],
        "memo": "・バンド２本",
        "unitPrice": null
      },
      {
        "target": "燃料タンク",
        "action": "点検",
        "positions": [],
        "memo": "・バンド２本",
        "unitPrice": null
      }
    ],
    "isSet": true,
    "status": "success",
    "errors": [],
    "setName": "燃料タンク点検・バンド２本取替",
    "setPrice": 5000
  },
  {
    "original": "ウィング後ろ左右リーンホースメント2個取替加工",
    "price": 136000,
    "invoiceId": "24123173-1",
    "items": [
      {
        "target": "ホース",
        "action": "取替",
        "positions": [],
        "memo": "ウィング後ろ左右リーンメント2個",
        "unitPrice": null
      },
      {
        "target": "ホース",
        "action": "加工",
        "positions": [],
        "memo": "ウィング後ろ左右リーンメント2個",
        "unitPrice": null
      }
    ],
    "isSet": true,
    "status": "success",
    "errors": [],
    "setName": "ウィング後ろ左右リーンホースメント2個取替加工",
    "setPrice": 136000
  },
  {
    "original": "観音扉キーブラケット交換",
    "price": 10000,
    "invoiceId": "24123174-1",
    "items": [
      {
        "target": "ブラケット",
        "action": "交換",
        "positions": [],
        "memo": "観音扉キー",
        "unitPrice": 10000
      }
    ],
    "isSet": false,
    "status": "success",
    "errors": []
  },
  {
    "original": "左サイドガード2番ステイ腐食部分切替・3番腐食部分コーナーパイプ製作切替・突っ張りパイプ切替・マーカーランプ脱着配線引替え・リフレクター貼替",
    "price": 48000,
    "invoiceId": "24123176-1",
    "items": [
      {
        "target": "サイドガード",
        "action": "脱着",
        "positions": [
          "左"
        ],
        "memo": "2番ステイ腐食部分・3番腐食部分コーナーパイプ切替・突っ張りパイプ切替・マーカーランプ配線引替え・リフレクター貼替",
        "unitPrice": null
      },
      {
        "target": "サイドガード",
        "action": "製作",
        "positions": [
          "左"
        ],
        "memo": "2番ステイ腐食部分・3番腐食部分コーナーパイプ切替・突っ張りパイプ切替・マーカーランプ配線引替え・リフレクター貼替",
        "unitPrice": null
      },
      {
        "target": "サイドガード",
        "action": "切替",
        "positions": [
          "左"
        ],
        "memo": "2番ステイ腐食部分・3番腐食部分コーナーパイプ切替・突っ張りパイプ切替・マーカーランプ配線引替え・リフレクター貼替",
        "unitPrice": null
      }
    ],
    "isSet": true,
    "status": "success",
    "errors": [],
    "setName": "左サイドガード2番ステイ腐食部分切替・3番腐食部分コーナーパイプ製作切替・突っ張りパイプ切替・マーカーランプ脱着配線引替え・リフレクター貼替",
    "setPrice": 48000
  },
  {
    "original": "右ドア内張脱着・ラッチ脱着清掃・アーム脱着修正・キーシリンダー脱着清掃",
    "price": 15000,
    "invoiceId": "24123177-1",
    "items": [
      {
        "target": "ドア",
        "action": "脱着",
        "positions": [
          "右"
        ],
        "memo": "内張・ラッチ脱着・アーム脱着・キーシリンダー脱着清掃",
        "unitPrice": null
      },
      {
        "target": "ドア",
        "action": "修正",
        "positions": [
          "右"
        ],
        "memo": "内張・ラッチ脱着・アーム脱着・キーシリンダー脱着清掃",
        "unitPrice": null
      },
      {
        "target": "ドア",
        "action": "清掃",
        "positions": [
          "右"
        ],
        "memo": "内張・ラッチ脱着・アーム脱着・キーシリンダー脱着清掃",
        "unitPrice": null
      }
    ],
    "isSet": true,
    "status": "success",
    "errors": [],
    "setName": "右ドア内張脱着・ラッチ脱着清掃・アーム脱着修正・キーシリンダー脱着清掃",
    "setPrice": 15000
  },
  {
    "original": "右バンパーフィニッシャー・コーナーカバー交換修正",
    "price": 8500,
    "invoiceId": "24123179-1",
    "items": [
      {
        "target": "バンパーフィニッシャー",
        "action": "カバー",
        "positions": [
          "右"
        ],
        "memo": "・コーナー",
        "unitPrice": null
      },
      {
        "target": "バンパーフィニッシャー",
        "action": "交換",
        "positions": [
          "右"
        ],
        "memo": "・コーナー",
        "unitPrice": null
      },
      {
        "target": "バンパーフィニッシャー",
        "action": "修正",
        "positions": [
          "右"
        ],
        "memo": "・コーナー",
        "unitPrice": null
      }
    ],
    "isSet": true,
    "status": "success",
    "errors": [],
    "setName": "右バンパーフィニッシャー・コーナーカバー交換修正",
    "setPrice": 8500
  },
  {
    "original": "右ヘッドライト・フォグランプ・フラッシャー交換",
    "price": 5500,
    "invoiceId": "24123179-1",
    "items": [
      {
        "target": "ヘッドライト",
        "action": "交換",
        "positions": [
          "右"
        ],
        "memo": "・フォグランプ・フラッシャー",
        "unitPrice": 5500
      }
    ],
    "isSet": false,
    "status": "success",
    "errors": []
  },
  {
    "original": "右コーナーパネル・アンダーカバー・配線ガード脱着",
    "price": 6500,
    "invoiceId": "24123179-1",
    "items": [
      {
        "target": "コーナーパネル",
        "action": "カバー",
        "positions": [
          "右"
        ],
        "memo": "・アンダー・配線ガード",
        "unitPrice": null
      },
      {
        "target": "コーナーパネル",
        "action": "脱着",
        "positions": [
          "右"
        ],
        "memo": "・アンダー・配線ガード",
        "unitPrice": null
      }
    ],
    "isSet": true,
    "status": "success",
    "errors": [],
    "setName": "右コーナーパネル・アンダーカバー・配線ガード脱着",
    "setPrice": 6500
  },
  {
    "original": "左右ファーストステップ脱着ステイ修正",
    "price": 15000,
    "invoiceId": "24123179-1",
    "items": [
      {
        "target": "ファーストステップ",
        "action": "脱着",
        "positions": [
          "左"
        ],
        "memo": "右ステイ",
        "unitPrice": null
      },
      {
        "target": "ファーストステップ",
        "action": "修正",
        "positions": [
          "左"
        ],
        "memo": "右ステイ",
        "unitPrice": null
      }
    ],
    "isSet": true,
    "status": "success",
    "errors": [],
    "setName": "左右ファーストステップ脱着ステイ修正",
    "setPrice": 15000
  },
  {
    "original": "フロントグリル・左フラッシャー・左ヘッドライト・左コーナーパネル脱着・左ドアストッパーボルト折れ込み修理",
    "price": 18000,
    "invoiceId": "24123180-1",
    "items": [
      {
        "target": "コーナーパネル",
        "action": "修理",
        "positions": [
          "フロント"
        ],
        "memo": "グリル・左フラッシャー・左ヘッドライト・左・左ドアストッパーボルト折れ込み",
        "unitPrice": null
      },
      {
        "target": "コーナーパネル",
        "action": "脱着",
        "positions": [
          "フロント"
        ],
        "memo": "グリル・左フラッシャー・左ヘッドライト・左・左ドアストッパーボルト折れ込み",
        "unitPrice": null
      }
    ],
    "isSet": true,
    "status": "success",
    "errors": [],
    "setName": "フロントグリル・左フラッシャー・左ヘッドライト・左コーナーパネル脱着・左ドアストッパーボルト折れ込み修理",
    "setPrice": 18000
  },
  {
    "original": "燃料タンクキャップ破壊交換",
    "price": 5000,
    "invoiceId": "24123181-1",
    "items": [
      {
        "target": "燃料タンク",
        "action": "交換",
        "positions": [],
        "memo": "キャップ破壊",
        "unitPrice": 5000
      }
    ],
    "isSet": false,
    "status": "success",
    "errors": []
  },
  {
    "original": "左サイドガード折損部切り替え加工溶接",
    "price": 12000,
    "invoiceId": "24123182-1",
    "items": [
      {
        "target": "サイドガード",
        "action": "加工",
        "positions": [
          "左"
        ],
        "memo": "折損部切り替え",
        "unitPrice": null
      },
      {
        "target": "サイドガード",
        "action": "溶接",
        "positions": [
          "左"
        ],
        "memo": "折損部切り替え",
        "unitPrice": null
      }
    ],
    "isSet": true,
    "status": "success",
    "errors": [],
    "setName": "左サイドガード折損部切り替え加工溶接",
    "setPrice": 12000
  },
  {
    "original": "テールパイプブッシュゴム取付",
    "price": 2000,
    "invoiceId": "24123185-1",
    "items": [
      {
        "target": "パイプ",
        "action": "取付",
        "positions": [],
        "memo": "テールブッシュゴム",
        "unitPrice": 2000
      }
    ],
    "isSet": false,
    "status": "success",
    "errors": []
  },
  {
    "original": "左右乗降ハンドル切断仕上げ",
    "price": 12000,
    "invoiceId": "24123191-1",
    "items": [
      {
        "target": "ハンドル",
        "action": "仕上げ",
        "positions": [
          "左"
        ],
        "memo": "右乗降",
        "unitPrice": null
      },
      {
        "target": "ハンドル",
        "action": "切断",
        "positions": [
          "左"
        ],
        "memo": "右乗降",
        "unitPrice": null
      }
    ],
    "isSet": true,
    "status": "success",
    "errors": [],
    "setName": "左右乗降ハンドル切断仕上げ",
    "setPrice": 12000
  },
  {
    "original": "マーカーランプ・パイプクランプ脱着加工",
    "price": 6000,
    "invoiceId": "24123191-1",
    "items": [
      {
        "target": "パイプ",
        "action": "加工",
        "positions": [],
        "memo": "マーカーランプ・クランプ",
        "unitPrice": null
      },
      {
        "target": "パイプ",
        "action": "脱着",
        "positions": [],
        "memo": "マーカーランプ・クランプ",
        "unitPrice": null
      }
    ],
    "isSet": true,
    "status": "success",
    "errors": [],
    "setName": "マーカーランプ・パイプクランプ脱着加工",
    "setPrice": 6000
  },
  {
    "original": "右前煽りドア補助装置取替",
    "price": 7500,
    "invoiceId": "24123192-1",
    "items": [
      {
        "target": "ドア",
        "action": "取替",
        "positions": [
          "右"
        ],
        "memo": "前煽り補助装置",
        "unitPrice": 7500
      }
    ],
    "isSet": false,
    "status": "success",
    "errors": []
  },
  {
    "original": "燃料タンク交換・バンド２本取替・サイドガードASSY脱着",
    "price": 18000,
    "invoiceId": "24123194-1",
    "items": [
      {
        "target": "サイドガード",
        "action": "取替",
        "positions": [],
        "memo": "燃料タンク・バンド２本・ASSY",
        "unitPrice": null
      },
      {
        "target": "サイドガード",
        "action": "交換",
        "positions": [],
        "memo": "燃料タンク・バンド２本・ASSY",
        "unitPrice": null
      },
      {
        "target": "サイドガード",
        "action": "脱着",
        "positions": [],
        "memo": "燃料タンク・バンド２本・ASSY",
        "unitPrice": null
      }
    ],
    "isSet": true,
    "status": "success",
    "errors": [],
    "setName": "燃料タンク交換・バンド２本取替・サイドガードASSY脱着",
    "setPrice": 18000
  },
  {
    "original": "踊り場左縞鋼板脱着・オイルタンクブラケット修正ボルト折れ込み修理",
    "price": 18000,
    "invoiceId": "24123195-1",
    "items": [
      {
        "target": "オイルタンク",
        "action": "修理",
        "positions": [],
        "memo": "踊り場左縞鋼板・ブラケットボルト折れ込み",
        "unitPrice": null
      },
      {
        "target": "オイルタンク",
        "action": "脱着",
        "positions": [],
        "memo": "踊り場左縞鋼板・ブラケットボルト折れ込み",
        "unitPrice": null
      },
      {
        "target": "オイルタンク",
        "action": "修正",
        "positions": [],
        "memo": "踊り場左縞鋼板・ブラケットボルト折れ込み",
        "unitPrice": null
      }
    ],
    "isSet": true,
    "status": "success",
    "errors": [],
    "setName": "踊り場左縞鋼板脱着・オイルタンクブラケット修正ボルト折れ込み修理",
    "setPrice": 18000
  },
  {
    "original": "左後ろ煽りドアキャッチ取替",
    "price": 2000,
    "invoiceId": "24123198-1",
    "items": [
      {
        "target": "ドア",
        "action": "取替",
        "positions": [
          "左"
        ],
        "memo": "後ろ煽りキャッチ",
        "unitPrice": 2000
      }
    ],
    "isSet": false,
    "status": "success",
    "errors": []
  },
  {
    "original": "中間エキゾーストパイプ腐食部分鉄板張り修理",
    "price": 38000,
    "invoiceId": "24123199-1",
    "items": [
      {
        "target": "パイプ",
        "action": "修理",
        "positions": [],
        "memo": "中間エキゾースト腐食部分鉄板張り",
        "unitPrice": 38000
      }
    ],
    "isSet": false,
    "status": "success",
    "errors": []
  },
  {
    "original": "左右サイドガードステップリベット打ち替え加工",
    "price": 6000,
    "invoiceId": "24123202-1",
    "items": [
      {
        "target": "サイドガード",
        "action": "加工",
        "positions": [
          "左"
        ],
        "memo": "右ステップリベット打ち替え",
        "unitPrice": 6000
      }
    ],
    "isSet": false,
    "status": "success",
    "errors": []
  },
  {
    "original": "ツイストロック分解点検・ブラケット曲がり直し溶接・マーカーランプ・ステイ脱着ボルト切断取替加工",
    "price": 18000,
    "invoiceId": "24123204-1",
    "items": [
      {
        "target": "ブラケット",
        "action": "曲がり直し",
        "positions": [],
        "memo": "ツイストロック・・マーカーランプ・ステイボルト",
        "unitPrice": null
      },
      {
        "target": "ブラケット",
        "action": "取替",
        "positions": [],
        "memo": "ツイストロック・・マーカーランプ・ステイボルト",
        "unitPrice": null
      },
      {
        "target": "ブラケット",
        "action": "加工",
        "positions": [],
        "memo": "ツイストロック・・マーカーランプ・ステイボルト",
        "unitPrice": null
      },
      {
        "target": "ブラケット",
        "action": "脱着",
        "positions": [],
        "memo": "ツイストロック・・マーカーランプ・ステイボルト",
        "unitPrice": null
      },
      {
        "target": "ブラケット",
        "action": "溶接",
        "positions": [],
        "memo": "ツイストロック・・マーカーランプ・ステイボルト",
        "unitPrice": null
      },
      {
        "target": "ブラケット",
        "action": "点検",
        "positions": [],
        "memo": "ツイストロック・・マーカーランプ・ステイボルト",
        "unitPrice": null
      },
      {
        "target": "ブラケット",
        "action": "切断",
        "positions": [],
        "memo": "ツイストロック・・マーカーランプ・ステイボルト",
        "unitPrice": null
      },
      {
        "target": "ブラケット",
        "action": "分解",
        "positions": [],
        "memo": "ツイストロック・・マーカーランプ・ステイボルト",
        "unitPrice": null
      }
    ],
    "isSet": true,
    "status": "success",
    "errors": [],
    "setName": "ツイストロック分解点検・ブラケット曲がり直し溶接・マーカーランプ・ステイ脱着ボルト切断取替加工",
    "setPrice": 18000
  },
  {
    "original": "バッテリー脱着・押えボルト製作取替・フックステイ折れ込みボルト6本修理・ステイ取付加工",
    "price": 24000,
    "invoiceId": "24123205-1",
    "items": [
      {
        "target": "バッテリー",
        "action": "取替",
        "positions": [],
        "memo": "・押えボルト・フックステイ折れ込みボルト6本・ステイ",
        "unitPrice": null
      },
      {
        "target": "バッテリー",
        "action": "加工",
        "positions": [],
        "memo": "・押えボルト・フックステイ折れ込みボルト6本・ステイ",
        "unitPrice": null
      },
      {
        "target": "バッテリー",
        "action": "修理",
        "positions": [],
        "memo": "・押えボルト・フックステイ折れ込みボルト6本・ステイ",
        "unitPrice": null
      },
      {
        "target": "バッテリー",
        "action": "脱着",
        "positions": [],
        "memo": "・押えボルト・フックステイ折れ込みボルト6本・ステイ",
        "unitPrice": null
      },
      {
        "target": "バッテリー",
        "action": "取付",
        "positions": [],
        "memo": "・押えボルト・フックステイ折れ込みボルト6本・ステイ",
        "unitPrice": null
      },
      {
        "target": "バッテリー",
        "action": "製作",
        "positions": [],
        "memo": "・押えボルト・フックステイ折れ込みボルト6本・ステイ",
        "unitPrice": null
      }
    ],
    "isSet": true,
    "status": "success",
    "errors": [],
    "setName": "バッテリー脱着・押えボルト製作取替・フックステイ折れ込みボルト6本修理・ステイ取付加工",
    "setPrice": 24000
  },
  {
    "original": "荷台ベアリング4個取替加工・ローラーブラケット補強取付ステン溶接",
    "price": 28000,
    "invoiceId": "25013206-1",
    "items": [
      {
        "target": "ブラケット",
        "action": "取替",
        "positions": [
          "荷台"
        ],
        "memo": "ベアリング4個・ローラー補強ステン",
        "unitPrice": null
      },
      {
        "target": "ブラケット",
        "action": "加工",
        "positions": [
          "荷台"
        ],
        "memo": "ベアリング4個・ローラー補強ステン",
        "unitPrice": null
      },
      {
        "target": "ブラケット",
        "action": "溶接",
        "positions": [
          "荷台"
        ],
        "memo": "ベアリング4個・ローラー補強ステン",
        "unitPrice": null
      },
      {
        "target": "ブラケット",
        "action": "取付",
        "positions": [
          "荷台"
        ],
        "memo": "ベアリング4個・ローラー補強ステン",
        "unitPrice": null
      }
    ],
    "isSet": true,
    "status": "success",
    "errors": [],
    "setName": "荷台ベアリング4個取替加工・ローラーブラケット補強取付ステン溶接",
    "setPrice": 28000
  },
  {
    "original": "左右サイドガード折損溶接３ヶ所",
    "price": 15000,
    "invoiceId": "25013216-1",
    "items": [
      {
        "target": "サイドガード",
        "action": "溶接",
        "positions": [
          "左"
        ],
        "memo": "右折損３ヶ所",
        "unitPrice": 15000
      }
    ],
    "isSet": false,
    "status": "success",
    "errors": []
  },
  {
    "original": "右テールランプブラケット製作取付加工・ブッシュゴム切断取替・テールランプ・リフレクター取付・青塗装",
    "price": 48000,
    "invoiceId": "25013218-1",
    "items": [
      {
        "target": "ブラケット",
        "action": "取替",
        "positions": [
          "右"
        ],
        "memo": "テールランプ・ブッシュゴム・テールランプ・リフレクター取付・青",
        "unitPrice": null
      },
      {
        "target": "ブラケット",
        "action": "加工",
        "positions": [
          "右"
        ],
        "memo": "テールランプ・ブッシュゴム・テールランプ・リフレクター取付・青",
        "unitPrice": null
      },
      {
        "target": "ブラケット",
        "action": "取付",
        "positions": [
          "右"
        ],
        "memo": "テールランプ・ブッシュゴム・テールランプ・リフレクター取付・青",
        "unitPrice": null
      },
      {
        "target": "ブラケット",
        "action": "製作",
        "positions": [
          "右"
        ],
        "memo": "テールランプ・ブッシュゴム・テールランプ・リフレクター取付・青",
        "unitPrice": null
      },
      {
        "target": "ブラケット",
        "action": "切断",
        "positions": [
          "右"
        ],
        "memo": "テールランプ・ブッシュゴム・テールランプ・リフレクター取付・青",
        "unitPrice": null
      },
      {
        "target": "ブラケット",
        "action": "塗装",
        "positions": [
          "右"
        ],
        "memo": "テールランプ・ブッシュゴム・テールランプ・リフレクター取付・青",
        "unitPrice": null
      }
    ],
    "isSet": true,
    "status": "success",
    "errors": [],
    "setName": "右テールランプブラケット製作取付加工・ブッシュゴム切断取替・テールランプ・リフレクター取付・青塗装",
    "setPrice": 48000
  },
  {
    "original": "アドブルーキャップ・燃料タンクキャップ2個シリンダー分解取替",
    "price": 9000,
    "invoiceId": "25013219-1",
    "items": [
      {
        "target": "燃料タンク",
        "action": "取替",
        "positions": [],
        "memo": "アドブルーキャップ・キャップ2個シリンダー",
        "unitPrice": null
      },
      {
        "target": "燃料タンク",
        "action": "分解",
        "positions": [],
        "memo": "アドブルーキャップ・キャップ2個シリンダー",
        "unitPrice": null
      }
    ],
    "isSet": true,
    "status": "success",
    "errors": [],
    "setName": "アドブルーキャップ・燃料タンクキャップ2個シリンダー分解取替",
    "setPrice": 9000
  },
  {
    "original": "左サイドミラー型違い取替加工",
    "price": 6000,
    "invoiceId": "25013220-1",
    "items": [
      {
        "target": "サイドミラー",
        "action": "取替",
        "positions": [
          "左"
        ],
        "memo": "型違い",
        "unitPrice": null
      },
      {
        "target": "サイドミラー",
        "action": "加工",
        "positions": [
          "左"
        ],
        "memo": "型違い",
        "unitPrice": null
      }
    ],
    "isSet": true,
    "status": "success",
    "errors": [],
    "setName": "左サイドミラー型違い取替加工",
    "setPrice": 6000
  },
  {
    "original": "リヤナンバーブラケット脱着鈑金修理",
    "price": 18000,
    "invoiceId": "25013221-1",
    "items": [
      {
        "target": "ブラケット",
        "action": "鈑金",
        "positions": [],
        "memo": "リヤナンバー脱着",
        "unitPrice": null
      },
      {
        "target": "ブラケット",
        "action": "修理",
        "positions": [],
        "memo": "リヤナンバー脱着",
        "unitPrice": null
      }
    ],
    "isSet": true,
    "status": "success",
    "errors": [],
    "setName": "リヤナンバーブラケット脱着鈑金修理",
    "setPrice": 18000
  },
  {
    "original": "燃料タンクキャップチェーン取付",
    "price": 600,
    "invoiceId": "25013223-1",
    "items": [
      {
        "target": "燃料タンク",
        "action": "取付",
        "positions": [],
        "memo": "キャップチェーン",
        "unitPrice": 600
      }
    ],
    "isSet": false,
    "status": "success",
    "errors": []
  },
  {
    "original": "左サイドガード切替加工溶接1本",
    "price": 12000,
    "invoiceId": "25013226-1",
    "items": [
      {
        "target": "サイドガード",
        "action": "加工",
        "positions": [
          "左"
        ],
        "memo": "1本",
        "unitPrice": null
      },
      {
        "target": "サイドガード",
        "action": "溶接",
        "positions": [
          "左"
        ],
        "memo": "1本",
        "unitPrice": null
      },
      {
        "target": "サイドガード",
        "action": "切替",
        "positions": [
          "左"
        ],
        "memo": "1本",
        "unitPrice": null
      }
    ],
    "isSet": true,
    "status": "success",
    "errors": [],
    "setName": "左サイドガード切替加工溶接1本",
    "setPrice": 12000
  },
  {
    "original": "右後ろツイストロックブラケット切断製作鈑金・反射板脱着・ツイストロック取替",
    "price": 180000,
    "invoiceId": "25013228-1",
    "items": [
      {
        "target": "ブラケット",
        "action": "鈑金",
        "positions": [
          "右",
          "後"
        ],
        "memo": "ろツイストロック・反射板・ツイストロック",
        "unitPrice": null
      },
      {
        "target": "ブラケット",
        "action": "取替",
        "positions": [
          "右",
          "後"
        ],
        "memo": "ろツイストロック・反射板・ツイストロック",
        "unitPrice": null
      },
      {
        "target": "ブラケット",
        "action": "脱着",
        "positions": [
          "右",
          "後"
        ],
        "memo": "ろツイストロック・反射板・ツイストロック",
        "unitPrice": null
      },
      {
        "target": "ブラケット",
        "action": "製作",
        "positions": [
          "右",
          "後"
        ],
        "memo": "ろツイストロック・反射板・ツイストロック",
        "unitPrice": null
      },
      {
        "target": "ブラケット",
        "action": "切断",
        "positions": [
          "右",
          "後"
        ],
        "memo": "ろツイストロック・反射板・ツイストロック",
        "unitPrice": null
      }
    ],
    "isSet": true,
    "status": "success",
    "errors": [],
    "setName": "右後ろツイストロックブラケット切断製作鈑金・反射板脱着・ツイストロック取替",
    "setPrice": 180000
  },
  {
    "original": "タイヤハウスカバー・マッドガード脱着・チルドシリンダー・ホース２本取替",
    "price": 25000,
    "invoiceId": "25013229-1",
    "items": [
      {
        "target": "タイヤハウスカバー",
        "action": "取替",
        "positions": [],
        "memo": "・マッドガード・チルドシリンダー・ホース２本",
        "unitPrice": null
      },
      {
        "target": "タイヤハウスカバー",
        "action": "脱着",
        "positions": [],
        "memo": "・マッドガード・チルドシリンダー・ホース２本",
        "unitPrice": null
      }
    ],
    "isSet": true,
    "status": "success",
    "errors": [],
    "setName": "タイヤハウスカバー・マッドガード脱着・チルドシリンダー・ホース２本取替",
    "setPrice": 25000
  },
  {
    "original": "バックカメラブラケット折れ込みボルト修理",
    "price": 10000,
    "invoiceId": "25013233-1",
    "items": [
      {
        "target": "ブラケット",
        "action": "修理",
        "positions": [],
        "memo": "バックカメラ折れ込みボルト",
        "unitPrice": 10000
      }
    ],
    "isSet": false,
    "status": "success",
    "errors": []
  },
  {
    "original": "右テールランプブラケット取替・反射板取替加工・テールランプ取り付け",
    "price": 15000,
    "invoiceId": "25013235-1",
    "items": [
      {
        "target": "ブラケット",
        "action": "取替",
        "positions": [
          "右"
        ],
        "memo": "テールランプ・反射板取替・テールランプ取り付け",
        "unitPrice": null
      },
      {
        "target": "ブラケット",
        "action": "加工",
        "positions": [
          "右"
        ],
        "memo": "テールランプ・反射板取替・テールランプ取り付け",
        "unitPrice": null
      }
    ],
    "isSet": true,
    "status": "success",
    "errors": [],
    "setName": "右テールランプブラケット取替・反射板取替加工・テールランプ取り付け",
    "setPrice": 15000
  },
  {
    "original": "左右サイドガード折損溶接6カ所",
    "price": 18000,
    "invoiceId": "25013236-1",
    "items": [
      {
        "target": "サイドガード",
        "action": "溶接",
        "positions": [
          "左"
        ],
        "memo": "右折損6カ所",
        "unitPrice": 18000
      }
    ],
    "isSet": false,
    "status": "success",
    "errors": []
  },
  {
    "original": "カプラースイッチブラケット加工",
    "price": 12000,
    "invoiceId": "25013240-1",
    "items": [
      {
        "target": "ブラケット",
        "action": "加工",
        "positions": [],
        "memo": "カプラースイッチ",
        "unitPrice": 12000
      }
    ],
    "isSet": false,
    "status": "success",
    "errors": []
  },
  {
    "original": "左ドア捻じれ修理・スイッチ加工",
    "price": 15000,
    "invoiceId": "25013241-1",
    "items": [
      {
        "target": "ドア",
        "action": "加工",
        "positions": [
          "左"
        ],
        "memo": "捻じれ・スイッチ",
        "unitPrice": null
      },
      {
        "target": "ドア",
        "action": "修理",
        "positions": [
          "左"
        ],
        "memo": "捻じれ・スイッチ",
        "unitPrice": null
      }
    ],
    "isSet": true,
    "status": "success",
    "errors": [],
    "setName": "左ドア捻じれ修理・スイッチ加工",
    "setPrice": 15000
  },
  {
    "original": "右ドア嚙み込み修理・内張脱着・ラッチ応急修理",
    "price": 24000,
    "invoiceId": "25013242-1",
    "items": [
      {
        "target": "ドア",
        "action": "修理",
        "positions": [
          "右"
        ],
        "memo": "嚙み込み・内張・ラッチ応急修理",
        "unitPrice": null
      },
      {
        "target": "ドア",
        "action": "脱着",
        "positions": [
          "右"
        ],
        "memo": "嚙み込み・内張・ラッチ応急修理",
        "unitPrice": null
      }
    ],
    "isSet": true,
    "status": "success",
    "errors": [],
    "setName": "右ドア嚙み込み修理・内張脱着・ラッチ応急修理",
    "setPrice": 24000
  },
  {
    "original": "左サイドガード・幌骨脱着・燃料タンク・キャップ・ユニット・バンド２本取替・中蓋付替え",
    "price": 24000,
    "invoiceId": "25013243-1",
    "items": [
      {
        "target": "サイドガード",
        "action": "取替",
        "positions": [
          "左"
        ],
        "memo": "・幌骨・燃料タンク・キャップ・ユニット・バンド２本・中蓋え",
        "unitPrice": null
      },
      {
        "target": "サイドガード",
        "action": "脱着",
        "positions": [
          "左"
        ],
        "memo": "・幌骨・燃料タンク・キャップ・ユニット・バンド２本・中蓋え",
        "unitPrice": null
      },
      {
        "target": "サイドガード",
        "action": "付替",
        "positions": [
          "左"
        ],
        "memo": "・幌骨・燃料タンク・キャップ・ユニット・バンド２本・中蓋え",
        "unitPrice": null
      }
    ],
    "isSet": true,
    "status": "success",
    "errors": [],
    "setName": "左サイドガード・幌骨脱着・燃料タンク・キャップ・ユニット・バンド２本取替・中蓋付替え",
    "setPrice": 24000
  },
  {
    "original": "フロントバンパー・左フィニッシャー・インナーバンパー・左ヘッドライト・フラッシャー・フォグランプ・カバー交換・他部品付替え",
    "price": 28000,
    "invoiceId": "25013244-1",
    "items": [
      {
        "target": "インナーバンパー",
        "action": "カバー",
        "positions": [
          "フロント"
        ],
        "memo": "バンパー・左フィニッシャー・・左ヘッドライト・フラッシャー・フォグランプ・・他部品え",
        "unitPrice": null
      },
      {
        "target": "インナーバンパー",
        "action": "交換",
        "positions": [
          "フロント"
        ],
        "memo": "バンパー・左フィニッシャー・・左ヘッドライト・フラッシャー・フォグランプ・・他部品え",
        "unitPrice": null
      },
      {
        "target": "インナーバンパー",
        "action": "付替",
        "positions": [
          "フロント"
        ],
        "memo": "バンパー・左フィニッシャー・・左ヘッドライト・フラッシャー・フォグランプ・・他部品え",
        "unitPrice": null
      }
    ],
    "isSet": true,
    "status": "success",
    "errors": [],
    "setName": "フロントバンパー・左フィニッシャー・インナーバンパー・左ヘッドライト・フラッシャー・フォグランプ・カバー交換・他部品付替え",
    "setPrice": 28000
  },
  {
    "original": "左コーナーパネル取替修正",
    "price": 8000,
    "invoiceId": "25013244-1",
    "items": [
      {
        "target": "コーナーパネル",
        "action": "取替",
        "positions": [
          "左"
        ],
        "memo": "",
        "unitPrice": null
      },
      {
        "target": "コーナーパネル",
        "action": "修正",
        "positions": [
          "左"
        ],
        "memo": "",
        "unitPrice": null
      }
    ],
    "isSet": true,
    "status": "success",
    "errors": [],
    "setName": "左コーナーパネル取替修正",
    "setPrice": 8000
  },
  {
    "original": "フロントグリル・左ステイ取替・取付ブラケット鈑金",
    "price": 14000,
    "invoiceId": "25013244-1",
    "items": [
      {
        "target": "ブラケット",
        "action": "鈑金",
        "positions": [
          "フロント"
        ],
        "memo": "グリル・左ステイ・",
        "unitPrice": null
      },
      {
        "target": "ブラケット",
        "action": "取替",
        "positions": [
          "フロント"
        ],
        "memo": "グリル・左ステイ・",
        "unitPrice": null
      },
      {
        "target": "ブラケット",
        "action": "取付",
        "positions": [
          "フロント"
        ],
        "memo": "グリル・左ステイ・",
        "unitPrice": null
      }
    ],
    "isSet": true,
    "status": "success",
    "errors": [],
    "setName": "フロントグリル・左ステイ取替・取付ブラケット鈑金",
    "setPrice": 14000
  },
  {
    "original": "フロントバンパー・インナーバンパー・左右ヘッドライト・フォグランプ・フラッシャー取替え",
    "price": 28000,
    "invoiceId": "25013245-1",
    "items": [
      {
        "target": "インナーバンパー",
        "action": "取替",
        "positions": [
          "フロント"
        ],
        "memo": "バンパー・・左右ヘッドライト・フォグランプ・フラッシャーえ",
        "unitPrice": 28000
      }
    ],
    "isSet": false,
    "status": "success",
    "errors": []
  },
  {
    "original": "右コーナーパネル脱着修正・アンダーカバー交換",
    "price": 6500,
    "invoiceId": "25013245-1",
    "items": [
      {
        "target": "コーナーパネル",
        "action": "カバー",
        "positions": [
          "右"
        ],
        "memo": "・アンダー",
        "unitPrice": null
      },
      {
        "target": "コーナーパネル",
        "action": "交換",
        "positions": [
          "右"
        ],
        "memo": "・アンダー",
        "unitPrice": null
      },
      {
        "target": "コーナーパネル",
        "action": "脱着",
        "positions": [
          "右"
        ],
        "memo": "・アンダー",
        "unitPrice": null
      },
      {
        "target": "コーナーパネル",
        "action": "修正",
        "positions": [
          "右"
        ],
        "memo": "・アンダー",
        "unitPrice": null
      }
    ],
    "isSet": true,
    "status": "success",
    "errors": [],
    "setName": "右コーナーパネル脱着修正・アンダーカバー交換",
    "setPrice": 6500
  },
  {
    "original": "右ドアパネルASSY・バイザー・ミラーアーム交換・部品組替",
    "price": 42000,
    "invoiceId": "25013245-1",
    "items": [
      {
        "target": "ドアパネル",
        "action": "交換",
        "positions": [
          "右"
        ],
        "memo": "ASSY・バイザー・ミラーアーム・部品",
        "unitPrice": null
      },
      {
        "target": "ドアパネル",
        "action": "組替",
        "positions": [
          "右"
        ],
        "memo": "ASSY・バイザー・ミラーアーム・部品",
        "unitPrice": null
      }
    ],
    "isSet": true,
    "status": "success",
    "errors": [],
    "setName": "右ドアパネルASSY・バイザー・ミラーアーム交換・部品組替",
    "setPrice": 42000
  },
  {
    "original": "右タイヤハウスカバー・脱着・アッパーフェンダー交換・取り付け部分修正",
    "price": 16000,
    "invoiceId": "25013245-1",
    "items": [
      {
        "target": "アッパーフェンダー",
        "action": "カバー",
        "positions": [
          "右"
        ],
        "memo": "タイヤハウス・・・取り付け部分",
        "unitPrice": null
      },
      {
        "target": "アッパーフェンダー",
        "action": "交換",
        "positions": [
          "右"
        ],
        "memo": "タイヤハウス・・・取り付け部分",
        "unitPrice": null
      },
      {
        "target": "アッパーフェンダー",
        "action": "脱着",
        "positions": [
          "右"
        ],
        "memo": "タイヤハウス・・・取り付け部分",
        "unitPrice": null
      },
      {
        "target": "アッパーフェンダー",
        "action": "修正",
        "positions": [
          "右"
        ],
        "memo": "タイヤハウス・・・取り付け部分",
        "unitPrice": null
      }
    ],
    "isSet": true,
    "status": "success",
    "errors": [],
    "setName": "右タイヤハウスカバー・脱着・アッパーフェンダー交換・取り付け部分修正",
    "setPrice": 16000
  },
  {
    "original": "右セカンドステップ・ロアフェンダー交換・取り付け部分修正",
    "price": 8500,
    "invoiceId": "25013245-1",
    "items": [
      {
        "target": "ロアフェンダー",
        "action": "交換",
        "positions": [
          "右",
          "セカンド"
        ],
        "memo": "ステップ・・取り付け部分",
        "unitPrice": null
      },
      {
        "target": "ロアフェンダー",
        "action": "修正",
        "positions": [
          "右",
          "セカンド"
        ],
        "memo": "ステップ・・取り付け部分",
        "unitPrice": null
      }
    ],
    "isSet": true,
    "status": "success",
    "errors": [],
    "setName": "右セカンドステップ・ロアフェンダー交換・取り付け部分修正",
    "setPrice": 8500
  },
  {
    "original": "左セカンドステップ脱着・ロアフェンダー交換・取り付け部分修正",
    "price": 8500,
    "invoiceId": "25013245-1",
    "items": [
      {
        "target": "セカンドステップ",
        "action": "交換",
        "positions": [
          "左"
        ],
        "memo": "・ロアフェンダー・取り付け部分",
        "unitPrice": null
      },
      {
        "target": "セカンドステップ",
        "action": "脱着",
        "positions": [
          "左"
        ],
        "memo": "・ロアフェンダー・取り付け部分",
        "unitPrice": null
      },
      {
        "target": "セカンドステップ",
        "action": "修正",
        "positions": [
          "左"
        ],
        "memo": "・ロアフェンダー・取り付け部分",
        "unitPrice": null
      }
    ],
    "isSet": true,
    "status": "success",
    "errors": [],
    "setName": "左セカンドステップ脱着・ロアフェンダー交換・取り付け部分修正",
    "setPrice": 8500
  },
  {
    "original": "左ファーストステップ・カバー脱着・ステイ修正",
    "price": 12000,
    "invoiceId": "25013245-1",
    "items": [
      {
        "target": "ファーストステップ",
        "action": "カバー",
        "positions": [
          "左"
        ],
        "memo": "・・ステイ",
        "unitPrice": null
      },
      {
        "target": "ファーストステップ",
        "action": "脱着",
        "positions": [
          "左"
        ],
        "memo": "・・ステイ",
        "unitPrice": null
      },
      {
        "target": "ファーストステップ",
        "action": "修正",
        "positions": [
          "左"
        ],
        "memo": "・・ステイ",
        "unitPrice": null
      }
    ],
    "isSet": true,
    "status": "success",
    "errors": [],
    "setName": "左ファーストステップ・カバー脱着・ステイ修正",
    "setPrice": 12000
  },
  {
    "original": "左スプラッシュシールゴム交換・タイヤハウスカバー脱着",
    "price": 8000,
    "invoiceId": "25013245-1",
    "items": [
      {
        "target": "タイヤハウスカバー",
        "action": "交換",
        "positions": [
          "左"
        ],
        "memo": "スプラッシュシールゴム・",
        "unitPrice": null
      },
      {
        "target": "タイヤハウスカバー",
        "action": "脱着",
        "positions": [
          "左"
        ],
        "memo": "スプラッシュシールゴム・",
        "unitPrice": null
      }
    ],
    "isSet": true,
    "status": "success",
    "errors": [],
    "setName": "左スプラッシュシールゴム交換・タイヤハウスカバー脱着",
    "setPrice": 8000
  },
  {
    "original": "左右マッドガード交換",
    "price": 8000,
    "invoiceId": "25013245-1",
    "items": [
      {
        "target": "マッドガード",
        "action": "交換",
        "positions": [
          "左"
        ],
        "memo": "右",
        "unitPrice": 8000
      }
    ],
    "isSet": false,
    "status": "success",
    "errors": []
  },
  {
    "original": "踊り場・工具箱脱着・エアタンク3本交換",
    "price": 48000,
    "invoiceId": "25013245-1",
    "items": [
      {
        "target": "エアタンク",
        "action": "交換",
        "positions": [],
        "memo": "踊り場・工具箱・3本",
        "unitPrice": null
      },
      {
        "target": "エアタンク",
        "action": "脱着",
        "positions": [],
        "memo": "踊り場・工具箱・3本",
        "unitPrice": null
      }
    ],
    "isSet": true,
    "status": "success",
    "errors": [],
    "setName": "踊り場・工具箱脱着・エアタンク3本交換",
    "setPrice": 48000
  },
  {
    "original": "右サイドガードASSY交換・マーカーステイ付替え鈑金加工",
    "price": 62000,
    "invoiceId": "25013245-1",
    "items": [
      {
        "target": "サイドガード",
        "action": "鈑金",
        "positions": [
          "右"
        ],
        "memo": "ASSY・マーカーステイえ",
        "unitPrice": null
      },
      {
        "target": "サイドガード",
        "action": "加工",
        "positions": [
          "右"
        ],
        "memo": "ASSY・マーカーステイえ",
        "unitPrice": null
      },
      {
        "target": "サイドガード",
        "action": "交換",
        "positions": [
          "右"
        ],
        "memo": "ASSY・マーカーステイえ",
        "unitPrice": null
      },
      {
        "target": "サイドガード",
        "action": "付替",
        "positions": [
          "右"
        ],
        "memo": "ASSY・マーカーステイえ",
        "unitPrice": null
      }
    ],
    "isSet": true,
    "status": "success",
    "errors": [],
    "setName": "右サイドガードASSY交換・マーカーステイ付替え鈑金加工",
    "setPrice": 62000
  },
  {
    "original": "左サイドガード修正・マーカーステイ切断脱着鈑金加工",
    "price": 48000,
    "invoiceId": "25013245-1",
    "items": [
      {
        "target": "サイドガード",
        "action": "鈑金",
        "positions": [
          "左"
        ],
        "memo": "・マーカーステイ",
        "unitPrice": null
      },
      {
        "target": "サイドガード",
        "action": "加工",
        "positions": [
          "左"
        ],
        "memo": "・マーカーステイ",
        "unitPrice": null
      },
      {
        "target": "サイドガード",
        "action": "脱着",
        "positions": [
          "左"
        ],
        "memo": "・マーカーステイ",
        "unitPrice": null
      },
      {
        "target": "サイドガード",
        "action": "修正",
        "positions": [
          "左"
        ],
        "memo": "・マーカーステイ",
        "unitPrice": null
      },
      {
        "target": "サイドガード",
        "action": "切断",
        "positions": [
          "左"
        ],
        "memo": "・マーカーステイ",
        "unitPrice": null
      }
    ],
    "isSet": true,
    "status": "success",
    "errors": [],
    "setName": "左サイドガード修正・マーカーステイ切断脱着鈑金加工",
    "setPrice": 48000
  },
  {
    "original": "右リヤフェンダーブラケット交換・戸当たりゴムステイ切断付替え加工",
    "price": 12000,
    "invoiceId": "25013245-1",
    "items": [
      {
        "target": "ブラケット",
        "action": "加工",
        "positions": [
          "右"
        ],
        "memo": "リヤフェンダー・戸当たりゴムステイえ",
        "unitPrice": null
      },
      {
        "target": "ブラケット",
        "action": "交換",
        "positions": [
          "右"
        ],
        "memo": "リヤフェンダー・戸当たりゴムステイえ",
        "unitPrice": null
      },
      {
        "target": "ブラケット",
        "action": "切断",
        "positions": [
          "右"
        ],
        "memo": "リヤフェンダー・戸当たりゴムステイえ",
        "unitPrice": null
      },
      {
        "target": "ブラケット",
        "action": "付替",
        "positions": [
          "右"
        ],
        "memo": "リヤフェンダー・戸当たりゴムステイえ",
        "unitPrice": null
      }
    ],
    "isSet": true,
    "status": "success",
    "errors": [],
    "setName": "右リヤフェンダーブラケット交換・戸当たりゴムステイ切断付替え加工",
    "setPrice": 12000
  },
  {
    "original": "マフラーカバー・ステイ取替取り付け部修正",
    "price": 14000,
    "invoiceId": "25013245-1",
    "items": [
      {
        "target": "マフラーカバー",
        "action": "取替",
        "positions": [],
        "memo": "・ステイ取り付け部",
        "unitPrice": null
      },
      {
        "target": "マフラーカバー",
        "action": "修正",
        "positions": [],
        "memo": "・ステイ取り付け部",
        "unitPrice": null
      }
    ],
    "isSet": true,
    "status": "success",
    "errors": [],
    "setName": "マフラーカバー・ステイ取替取り付け部修正",
    "setPrice": 14000
  },
  {
    "original": "左サイドガード穴掘り切断ステン溶接取替加工・研磨・横根太ステイ切断付替え加工",
    "price": 118000,
    "invoiceId": "25013246-1",
    "items": [
      {
        "target": "サイドガード",
        "action": "取替",
        "positions": [
          "左"
        ],
        "memo": "穴掘りステン・・横根太ステイ切断え加工",
        "unitPrice": null
      },
      {
        "target": "サイドガード",
        "action": "加工",
        "positions": [
          "左"
        ],
        "memo": "穴掘りステン・・横根太ステイ切断え加工",
        "unitPrice": null
      },
      {
        "target": "サイドガード",
        "action": "溶接",
        "positions": [
          "左"
        ],
        "memo": "穴掘りステン・・横根太ステイ切断え加工",
        "unitPrice": null
      },
      {
        "target": "サイドガード",
        "action": "切断",
        "positions": [
          "左"
        ],
        "memo": "穴掘りステン・・横根太ステイ切断え加工",
        "unitPrice": null
      },
      {
        "target": "サイドガード",
        "action": "付替",
        "positions": [
          "左"
        ],
        "memo": "穴掘りステン・・横根太ステイ切断え加工",
        "unitPrice": null
      },
      {
        "target": "サイドガード",
        "action": "研磨",
        "positions": [
          "左"
        ],
        "memo": "穴掘りステン・・横根太ステイ切断え加工",
        "unitPrice": null
      }
    ],
    "isSet": true,
    "status": "success",
    "errors": [],
    "setName": "左サイドガード穴掘り切断ステン溶接取替加工・研磨・横根太ステイ切断付替え加工",
    "setPrice": 118000
  },
  {
    "original": "燃料タンク・ブラケット2本・バンド２本取替",
    "price": 28000,
    "invoiceId": "25013246-1",
    "items": [
      {
        "target": "ブラケット",
        "action": "取替",
        "positions": [],
        "memo": "燃料タンク・2本・バンド２本",
        "unitPrice": 28000
      }
    ],
    "isSet": false,
    "status": "success",
    "errors": []
  },
  {
    "original": "アドブルータンクステイ修正",
    "price": 12000,
    "invoiceId": "25013246-1",
    "items": [
      {
        "target": "アドブルータンク",
        "action": "修正",
        "positions": [],
        "memo": "ステイ",
        "unitPrice": 12000
      }
    ],
    "isSet": false,
    "status": "success",
    "errors": []
  },
  {
    "original": "エアードライヤー脱着・ブラケット取替",
    "price": 18000,
    "invoiceId": "25013246-1",
    "items": [
      {
        "target": "ブラケット",
        "action": "取替",
        "positions": [],
        "memo": "エアードライヤー・",
        "unitPrice": null
      },
      {
        "target": "ブラケット",
        "action": "脱着",
        "positions": [],
        "memo": "エアードライヤー・",
        "unitPrice": null
      }
    ],
    "isSet": true,
    "status": "success",
    "errors": [],
    "setName": "エアードライヤー脱着・ブラケット取替",
    "setPrice": 18000
  },
  {
    "original": "左サイドセンサー付替え・ステイ交換",
    "price": 15000,
    "invoiceId": "25013246-1",
    "items": [
      {
        "target": "サイドセンサー",
        "action": "交換",
        "positions": [
          "左"
        ],
        "memo": "え・ステイ",
        "unitPrice": null
      },
      {
        "target": "サイドセンサー",
        "action": "付替",
        "positions": [
          "左"
        ],
        "memo": "え・ステイ",
        "unitPrice": null
      }
    ],
    "isSet": true,
    "status": "success",
    "errors": [],
    "setName": "左サイドセンサー付替え・ステイ交換",
    "setPrice": 15000
  },
  {
    "original": "左マッドガード取替・ステイ取替",
    "price": 12000,
    "invoiceId": "25013246-1",
    "items": [
      {
        "target": "マッドガード",
        "action": "取替",
        "positions": [
          "左"
        ],
        "memo": "・ステイ取替",
        "unitPrice": 12000
      }
    ],
    "isSet": false,
    "status": "success",
    "errors": []
  },
  {
    "original": "左タイヤハウスカバー・セカンドステップ脱着・ロアフェンダー交換",
    "price": 18000,
    "invoiceId": "25013246-1",
    "items": [
      {
        "target": "タイヤハウスカバー",
        "action": "交換",
        "positions": [
          "左"
        ],
        "memo": "・セカンドステップ・ロアフェンダー",
        "unitPrice": null
      },
      {
        "target": "タイヤハウスカバー",
        "action": "脱着",
        "positions": [
          "左"
        ],
        "memo": "・セカンドステップ・ロアフェンダー",
        "unitPrice": null
      }
    ],
    "isSet": true,
    "status": "success",
    "errors": [],
    "setName": "左タイヤハウスカバー・セカンドステップ脱着・ロアフェンダー交換",
    "setPrice": 18000
  },
  {
    "original": "左ファーストステップ・カバー・ブラケット取替",
    "price": 18000,
    "invoiceId": "25013246-1",
    "items": [
      {
        "target": "ファーストステップ",
        "action": "カバー",
        "positions": [
          "左"
        ],
        "memo": "・・ブラケット",
        "unitPrice": null
      },
      {
        "target": "ファーストステップ",
        "action": "取替",
        "positions": [
          "左"
        ],
        "memo": "・・ブラケット",
        "unitPrice": null
      }
    ],
    "isSet": true,
    "status": "success",
    "errors": [],
    "setName": "左ファーストステップ・カバー・ブラケット取替",
    "setPrice": 18000
  },
  {
    "original": "左フィニッシャー・エンドカバー取替・取り付け部修正",
    "price": 10000,
    "invoiceId": "25013246-1",
    "items": [
      {
        "target": "エンドカバー",
        "action": "取替",
        "positions": [
          "左"
        ],
        "memo": "フィニッシャー・・取り付け部",
        "unitPrice": null
      },
      {
        "target": "エンドカバー",
        "action": "修正",
        "positions": [
          "左"
        ],
        "memo": "フィニッシャー・・取り付け部",
        "unitPrice": null
      }
    ],
    "isSet": true,
    "status": "success",
    "errors": [],
    "setName": "左フィニッシャー・エンドカバー取替・取り付け部修正",
    "setPrice": 10000
  },
  {
    "original": "左ヘッドライト交換・フォグランプ脱着・ステイ修正",
    "price": 10000,
    "invoiceId": "25013246-1",
    "items": [
      {
        "target": "ヘッドライト",
        "action": "交換",
        "positions": [
          "左"
        ],
        "memo": "・フォグランプ・ステイ",
        "unitPrice": null
      },
      {
        "target": "ヘッドライト",
        "action": "脱着",
        "positions": [
          "左"
        ],
        "memo": "・フォグランプ・ステイ",
        "unitPrice": null
      },
      {
        "target": "ヘッドライト",
        "action": "修正",
        "positions": [
          "左"
        ],
        "memo": "・フォグランプ・ステイ",
        "unitPrice": null
      }
    ],
    "isSet": true,
    "status": "success",
    "errors": [],
    "setName": "左ヘッドライト交換・フォグランプ脱着・ステイ修正",
    "setPrice": 10000
  },
  {
    "original": "フロントバンパー・インナーバンパー鈑金",
    "price": 12000,
    "invoiceId": "25013246-1",
    "items": [
      {
        "target": "インナーバンパー",
        "action": "鈑金",
        "positions": [
          "フロント"
        ],
        "memo": "バンパー・",
        "unitPrice": 12000
      }
    ],
    "isSet": false,
    "status": "success",
    "errors": []
  },
  {
    "original": "エアーパイプ1本取替",
    "price": 6000,
    "invoiceId": "25013246-1",
    "items": [
      {
        "target": "パイプ",
        "action": "取替",
        "positions": [],
        "memo": "エアー1本",
        "unitPrice": 6000
      }
    ],
    "isSet": false,
    "status": "success",
    "errors": []
  },
  {
    "original": "燃料タンク渡りホースコック・メクラプラグ交換",
    "price": 15000,
    "invoiceId": "25023248-1",
    "items": [
      {
        "target": "燃料タンク",
        "action": "交換",
        "positions": [],
        "memo": "渡りホースコック・メクラプラグ",
        "unitPrice": 15000
      }
    ],
    "isSet": false,
    "status": "success",
    "errors": []
  },
  {
    "original": "燃料タンク・ユニット・バンド２本・ブラケット2本取替",
    "price": 28000,
    "invoiceId": "25023249-1",
    "items": [
      {
        "target": "ブラケット",
        "action": "取替",
        "positions": [],
        "memo": "燃料タンク・ユニット・バンド２本・2本",
        "unitPrice": 28000
      }
    ],
    "isSet": false,
    "status": "success",
    "errors": []
  },
  {
    "original": "左サイドガード・マーカーランプ4こ・タイヤ灯・ステップ脱着・サイドガード鈑金塗装",
    "price": 32000,
    "invoiceId": "25023249-1",
    "items": [
      {
        "target": "サイドガード",
        "action": "鈑金",
        "positions": [
          "左"
        ],
        "memo": "・マーカーランプ4こ・タイヤ灯・ステップ・サイドガード",
        "unitPrice": null
      },
      {
        "target": "サイドガード",
        "action": "脱着",
        "positions": [
          "左"
        ],
        "memo": "・マーカーランプ4こ・タイヤ灯・ステップ・サイドガード",
        "unitPrice": null
      },
      {
        "target": "サイドガード",
        "action": "塗装",
        "positions": [
          "左"
        ],
        "memo": "・マーカーランプ4こ・タイヤ灯・ステップ・サイドガード",
        "unitPrice": null
      }
    ],
    "isSet": true,
    "status": "success",
    "errors": [],
    "setName": "左サイドガード・マーカーランプ4こ・タイヤ灯・ステップ脱着・サイドガード鈑金塗装",
    "setPrice": 32000
  },
  {
    "original": "右ウィングホース取替加工・泥除けプレート脱着・テールランプ配線引き換え・支柱清掃",
    "price": 68000,
    "invoiceId": "25023254-1",
    "items": [
      {
        "target": "ホース",
        "action": "取替",
        "positions": [
          "右"
        ],
        "memo": "ウィング・泥除けプレート・テールランプ配線引き換え・支柱",
        "unitPrice": null
      },
      {
        "target": "ホース",
        "action": "加工",
        "positions": [
          "右"
        ],
        "memo": "ウィング・泥除けプレート・テールランプ配線引き換え・支柱",
        "unitPrice": null
      },
      {
        "target": "ホース",
        "action": "脱着",
        "positions": [
          "右"
        ],
        "memo": "ウィング・泥除けプレート・テールランプ配線引き換え・支柱",
        "unitPrice": null
      },
      {
        "target": "ホース",
        "action": "清掃",
        "positions": [
          "右"
        ],
        "memo": "ウィング・泥除けプレート・テールランプ配線引き換え・支柱",
        "unitPrice": null
      }
    ],
    "isSet": true,
    "status": "success",
    "errors": [],
    "setName": "右ウィングホース取替加工・泥除けプレート脱着・テールランプ配線引き換え・支柱清掃",
    "setPrice": 68000
  },
  {
    "original": "テールパイプバンド脱着・折損部分製作取付溶接",
    "price": 10000,
    "invoiceId": "25023264-1",
    "items": [
      {
        "target": "パイプ",
        "action": "脱着",
        "positions": [],
        "memo": "テールバンド・折損部分",
        "unitPrice": null
      },
      {
        "target": "パイプ",
        "action": "溶接",
        "positions": [],
        "memo": "テールバンド・折損部分",
        "unitPrice": null
      },
      {
        "target": "パイプ",
        "action": "取付",
        "positions": [],
        "memo": "テールバンド・折損部分",
        "unitPrice": null
      },
      {
        "target": "パイプ",
        "action": "製作",
        "positions": [],
        "memo": "テールバンド・折損部分",
        "unitPrice": null
      }
    ],
    "isSet": true,
    "status": "success",
    "errors": [],
    "setName": "テールパイプバンド脱着・折損部分製作取付溶接",
    "setPrice": 10000
  },
  {
    "original": "左サイドガード脱着・メイン燃料タンク・バンド取替・敷ゴム2本製作貼替え",
    "price": 28800,
    "invoiceId": "25023269-1",
    "items": [
      {
        "target": "サイドガード",
        "action": "取替",
        "positions": [
          "左"
        ],
        "memo": "・メイン燃料タンク・バンド・敷ゴム2本貼替え",
        "unitPrice": null
      },
      {
        "target": "サイドガード",
        "action": "脱着",
        "positions": [
          "左"
        ],
        "memo": "・メイン燃料タンク・バンド・敷ゴム2本貼替え",
        "unitPrice": null
      },
      {
        "target": "サイドガード",
        "action": "製作",
        "positions": [
          "左"
        ],
        "memo": "・メイン燃料タンク・バンド・敷ゴム2本貼替え",
        "unitPrice": null
      }
    ],
    "isSet": true,
    "status": "success",
    "errors": [],
    "setName": "左サイドガード脱着・メイン燃料タンク・バンド取替・敷ゴム2本製作貼替え",
    "setPrice": 28800
  },
  {
    "original": "ウィング蝶番点検・グリスアップ・煽りキャッチハンドル曲がり修正",
    "price": 8000,
    "invoiceId": "25023270-1",
    "items": [
      {
        "target": "ハンドル",
        "action": "修正",
        "positions": [],
        "memo": "ウィング蝶番・グリスアップ・煽りキャッチ曲がり",
        "unitPrice": null
      },
      {
        "target": "ハンドル",
        "action": "点検",
        "positions": [],
        "memo": "ウィング蝶番・グリスアップ・煽りキャッチ曲がり",
        "unitPrice": null
      }
    ],
    "isSet": true,
    "status": "success",
    "errors": [],
    "setName": "ウィング蝶番点検・グリスアップ・煽りキャッチハンドル曲がり修正",
    "setPrice": 8000
  },
  {
    "original": "左バックミラー・アーム交換・アンダーミラー付替え",
    "price": 7000,
    "invoiceId": "25023272-1",
    "items": [
      {
        "target": "アンダーミラー",
        "action": "交換",
        "positions": [
          "左"
        ],
        "memo": "バックミラー・アーム・え",
        "unitPrice": null
      },
      {
        "target": "アンダーミラー",
        "action": "付替",
        "positions": [
          "左"
        ],
        "memo": "バックミラー・アーム・え",
        "unitPrice": null
      }
    ],
    "isSet": true,
    "status": "success",
    "errors": [],
    "setName": "左バックミラー・アーム交換・アンダーミラー付替え",
    "setPrice": 7000
  },
  {
    "original": "右中央煽りドアコーナーポスト脱着リベット打ち替え・キャッチ受け脱着下駄製作取付加工・全面キャッチ受け増し締め点検",
    "price": 28000,
    "invoiceId": "25023273-1",
    "items": [
      {
        "target": "ドア",
        "action": "加工",
        "positions": [
          "右"
        ],
        "memo": "中央煽りコーナーポストリベット打ち替え・キャッチ受け脱着下駄・全面キャッチ受け増し締め",
        "unitPrice": null
      },
      {
        "target": "ドア",
        "action": "脱着",
        "positions": [
          "右"
        ],
        "memo": "中央煽りコーナーポストリベット打ち替え・キャッチ受け脱着下駄・全面キャッチ受け増し締め",
        "unitPrice": null
      },
      {
        "target": "ドア",
        "action": "取付",
        "positions": [
          "右"
        ],
        "memo": "中央煽りコーナーポストリベット打ち替え・キャッチ受け脱着下駄・全面キャッチ受け増し締め",
        "unitPrice": null
      },
      {
        "target": "ドア",
        "action": "製作",
        "positions": [
          "右"
        ],
        "memo": "中央煽りコーナーポストリベット打ち替え・キャッチ受け脱着下駄・全面キャッチ受け増し締め",
        "unitPrice": null
      },
      {
        "target": "ドア",
        "action": "点検",
        "positions": [
          "右"
        ],
        "memo": "中央煽りコーナーポストリベット打ち替え・キャッチ受け脱着下駄・全面キャッチ受け増し締め",
        "unitPrice": null
      }
    ],
    "isSet": true,
    "status": "success",
    "errors": [],
    "setName": "右中央煽りドアコーナーポスト脱着リベット打ち替え・キャッチ受け脱着下駄製作取付加工・全面キャッチ受け増し締め点検",
    "setPrice": 28000
  },
  {
    "original": "左サイドガード脱着・ボルト切断取替加工",
    "price": 12000,
    "invoiceId": "25023277-1",
    "items": [
      {
        "target": "サイドガード",
        "action": "取替",
        "positions": [
          "左"
        ],
        "memo": "・ボルト",
        "unitPrice": null
      },
      {
        "target": "サイドガード",
        "action": "加工",
        "positions": [
          "左"
        ],
        "memo": "・ボルト",
        "unitPrice": null
      },
      {
        "target": "サイドガード",
        "action": "脱着",
        "positions": [
          "左"
        ],
        "memo": "・ボルト",
        "unitPrice": null
      },
      {
        "target": "サイドガード",
        "action": "切断",
        "positions": [
          "左"
        ],
        "memo": "・ボルト",
        "unitPrice": null
      }
    ],
    "isSet": true,
    "status": "success",
    "errors": [],
    "setName": "左サイドガード脱着・ボルト切断取替加工",
    "setPrice": 12000
  },
  {
    "original": "ナンバープレートブラケット曲がり修正",
    "price": 12000,
    "invoiceId": "25023278-1",
    "items": [
      {
        "target": "ブラケット",
        "action": "修正",
        "positions": [],
        "memo": "ナンバープレート曲がり",
        "unitPrice": 12000
      }
    ],
    "isSet": false,
    "status": "success",
    "errors": []
  },
  {
    "original": "ドライバーシート脱着・サスペンションブラケット点検増し締め",
    "price": 14000,
    "invoiceId": "25023280-1",
    "items": [
      {
        "target": "ブラケット",
        "action": "脱着",
        "positions": [],
        "memo": "ドライバーシート・サスペンション増し締め",
        "unitPrice": null
      },
      {
        "target": "ブラケット",
        "action": "点検",
        "positions": [],
        "memo": "ドライバーシート・サスペンション増し締め",
        "unitPrice": null
      }
    ],
    "isSet": true,
    "status": "success",
    "errors": [],
    "setName": "ドライバーシート脱着・サスペンションブラケット点検増し締め",
    "setPrice": 14000
  },
  {
    "original": "右ドア内張脱着・ラッチ交換・ストライカー交換",
    "price": 18000,
    "invoiceId": "25023281-1",
    "items": [
      {
        "target": "ドア",
        "action": "交換",
        "positions": [
          "右"
        ],
        "memo": "内張・ラッチ・ストライカー交換",
        "unitPrice": null
      },
      {
        "target": "ドア",
        "action": "脱着",
        "positions": [
          "右"
        ],
        "memo": "内張・ラッチ・ストライカー交換",
        "unitPrice": null
      }
    ],
    "isSet": true,
    "status": "success",
    "errors": [],
    "setName": "右ドア内張脱着・ラッチ交換・ストライカー交換",
    "setPrice": 18000
  },
  {
    "original": "左後ろタイヤハウスカバー脱着リベット打ち替え加工・蝶番脱着曲がり直し・床枠応急下駄製作取付加工",
    "price": 58000,
    "invoiceId": "25023284-1",
    "items": [
      {
        "target": "タイヤハウスカバー",
        "action": "曲がり直し",
        "positions": [
          "左"
        ],
        "memo": "後ろリベット打ち替え・蝶番脱着・床枠応急下駄加工",
        "unitPrice": null
      },
      {
        "target": "タイヤハウスカバー",
        "action": "加工",
        "positions": [
          "左"
        ],
        "memo": "後ろリベット打ち替え・蝶番脱着・床枠応急下駄加工",
        "unitPrice": null
      },
      {
        "target": "タイヤハウスカバー",
        "action": "脱着",
        "positions": [
          "左"
        ],
        "memo": "後ろリベット打ち替え・蝶番脱着・床枠応急下駄加工",
        "unitPrice": null
      },
      {
        "target": "タイヤハウスカバー",
        "action": "取付",
        "positions": [
          "左"
        ],
        "memo": "後ろリベット打ち替え・蝶番脱着・床枠応急下駄加工",
        "unitPrice": null
      },
      {
        "target": "タイヤハウスカバー",
        "action": "製作",
        "positions": [
          "左"
        ],
        "memo": "後ろリベット打ち替え・蝶番脱着・床枠応急下駄加工",
        "unitPrice": null
      }
    ],
    "isSet": true,
    "status": "success",
    "errors": [],
    "setName": "左後ろタイヤハウスカバー脱着リベット打ち替え加工・蝶番脱着曲がり直し・床枠応急下駄製作取付加工",
    "setPrice": 58000
  },
  {
    "original": "左ステンレスサイドガード脱着曲がり直し・ステイ脱着曲がり直し・仕切り板脱着曲がり直し・タイヤ灯脱着・スペアタイヤ脱着",
    "price": 68000,
    "invoiceId": "25033289-1",
    "items": [
      {
        "target": "サイドガード",
        "action": "曲がり直し",
        "positions": [
          "左"
        ],
        "memo": "ステンレス・ステイ脱着曲がり直し・仕切り板脱着曲がり直し・タイヤ灯脱着・スペアタイヤ脱着",
        "unitPrice": null
      },
      {
        "target": "サイドガード",
        "action": "脱着",
        "positions": [
          "左"
        ],
        "memo": "ステンレス・ステイ脱着曲がり直し・仕切り板脱着曲がり直し・タイヤ灯脱着・スペアタイヤ脱着",
        "unitPrice": null
      }
    ],
    "isSet": true,
    "status": "success",
    "errors": [],
    "setName": "左ステンレスサイドガード脱着曲がり直し・ステイ脱着曲がり直し・仕切り板脱着曲がり直し・タイヤ灯脱着・スペアタイヤ脱着",
    "setPrice": 68000
  }
]